pybluemonday-0.0.14.dist-info/LICENSE
pybluemonday-0.0.14.dist-info/METADATA
pybluemonday-0.0.14.dist-info/RECORD
pybluemonday-0.0.14.dist-info/WHEEL
pybluemonday-0.0.14.dist-info/top_level.txt
tests/test_memory_leaks.py
tests/__init__.py
tests/bluemonday/test_policies.py
tests/bluemonday/test_sanitize.py
tests/bluemonday/__init__.py
tests/html_sanitizer/test_sanitize.py
tests/html_sanitizer/__init__.py
pybluemonday/bluemonday.cpython-310-aarch64-linux-gnu.h
pybluemonday/bluemonday.cpython-310-aarch64-linux-gnu.so
pybluemonday/__init__.py
