Metadata-Version: 2.1
Name: pybluemonday
Version: 0.0.14
Summary: Python bindings for the bluemonday HTML sanitizer
Home-page: https://github.com/ColdHeat/pybluemonday
Author: Kevin Chung
Author-email: kchung@nyu.edu
Classifier: Programming Language :: Python :: 3
Classifier: License :: OSI Approved :: MIT License
Classifier: Operating System :: OS Independent
Requires-Python: >=3.7
License-File: LICENSE
Requires-Dist: cffi ~=1.1
